COPYING
MANIFEST.in
README.md
setup.py
jappy/__init__.py
jappy/hooks.py
jappy/server.py
jappy/webview.py
jappy.egg-info/PKG-INFO
jappy.egg-info/SOURCES.txt
jappy.egg-info/dependency_links.txt
jappy.egg-info/entry_points.txt
jappy.egg-info/requires.txt
jappy.egg-info/top_level.txt
jappy/webapp/Makefile
jappy/webapp/favicon.ico
jappy/webapp/index.html
jappy/webapp/jappy.json
jappy/webapp/manifest.json
jappy/webapp/package.json
jappy/webapp/setup.py
jappy/webapp/sw.js
jappy/webapp/template.html
jappy/webapp/yarn.lock
jappy/webapp/activity/activity-icon.svg
jappy/webapp/activity/activity.info
jappy/webapp/activity/jappy.png
jappy/webapp/activity/jappy.svg
jappy/webapp/css/.activity.css.swo
jappy/webapp/css/activity.css
jappy/webapp/css/github-markdown.css
jappy/webapp/css/markdown-extra.css
jappy/webapp/css/small-screens.css
jappy/webapp/css/tiny-screens.css
jappy/webapp/examples/geolocation.pyj
jappy/webapp/examples/input.pyj
jappy/webapp/examples/lunita.pyj
jappy/webapp/examples/mandala.pyj
jappy/webapp/examples/memorize.pyj
jappy/webapp/examples/repl.pyj
jappy/webapp/examples/unicode.pyj
jappy/webapp/examples/welcome.pyj
jappy/webapp/fonts/NotoEmoji.woff
jappy/webapp/icons/activity-icon.svg
jappy/webapp/icons/activity-start.svg
jappy/webapp/icons/document-generic.svg
jappy/webapp/icons/entry-search.svg
jappy/webapp/icons/eraser_bw.svg
jappy/webapp/icons/eraser_color.svg
jappy/webapp/icons/export-or-publish.svg
jappy/webapp/icons/folder.svg
jappy/webapp/icons/image-x-generic.svg
jappy/webapp/icons/load-example.svg
jappy/webapp/icons/run_bw.svg
jappy/webapp/icons/run_color.svg
jappy/webapp/icons/stopit_bw.svg
jappy/webapp/icons/stopit_color.svg
jappy/webapp/icons/tab-add.svg
jappy/webapp/icons/text-html.svg
jappy/webapp/icons/tray-hide.svg
jappy/webapp/icons/tray-show.svg
jappy/webapp/icons/user-documents.svg
jappy/webapp/icons/view-fullscreen.svg
jappy/webapp/icons/view-return.svg
jappy/webapp/icons/zip-archive.svg
jappy/webapp/icons/ios/ios-appicon-120-120.png
jappy/webapp/icons/ios/ios-appicon-152-152.png
jappy/webapp/icons/ios/ios-appicon-180-180.png
jappy/webapp/icons/ios/ios-appicon-76-76.png
jappy/webapp/js/activity.js
