Metadata-Version: 1.1
Name: jappy
Version: 0.2.0a15
Summary: A Python IDE for the Web
Home-page: https://github.com/somosazucar/Jappy
Author: SomosAzucar R&D Team
Author-email: equipo@somosazucar.org
License: UNKNOWN
Keywords: web rapydscript jappy html javascript webapp
Platform: UNKNOWN
Classifier: Development Status :: 3 - Alpha
Classifier: Intended Audience :: Developers
Classifier: Topic :: Text Editors :: Integrated Development Environments (IDE)
Classifier: License :: OSI Approved :: GNU Affero General Public License v3 or later (AGPLv3+)
Classifier: Programming Language :: Python :: 2
Classifier: Programming Language :: Python :: 2.7
Classifier: Programming Language :: Python :: 3
Classifier: Programming Language :: Python :: 3.4
Classifier: Programming Language :: Python :: 3.5
Classifier: Programming Language :: Python :: 3.6
